hatch_cmake/__init__.py
hatch_cmake/tests/test_all.py
hatch_cmake-0.1.0.dist-info/METADATA
hatch_cmake-0.1.0.dist-info/WHEEL
hatch_cmake-0.1.0.dist-info/licenses/LICENSE
hatch_cmake-0.1.0.dist-info/RECORD
