Metadata-Version: 2.4
Name: hatch-cmake
Version: 0.1.0
Summary: Hatch plugin for CMake/C++ builds
Project-URL: Repository, https://github.com/python-project-templates/hatch-cmake
Project-URL: Homepage, https://github.com/python-project-templates/hatch-cmake
Author-email: the hatch-cmake authors <t.paine154@gmail.com>
License: Apache-2.0
License-File: LICENSE
Keywords: build,c++,cmake,cpp,hatch,python
Classifier: Development Status :: 3 - Alpha
Classifier: Programming Language :: Python
Classifier: Programming Language :: Python :: 3
Classifier: Programming Language :: Python :: 3.9
Classifier: Programming Language :: Python :: 3.10
Classifier: Programming Language :: Python :: 3.11
Classifier: Programming Language :: Python :: 3.12
Classifier: Programming Language :: Python :: Implementation :: CPython
Classifier: Programming Language :: Python :: Implementation :: PyPy
Requires-Python: >=3.9
Requires-Dist: hatch-cpp
Provides-Extra: develop
Requires-Dist: build; extra == 'develop'
Requires-Dist: bump-my-version; extra == 'develop'
Requires-Dist: check-manifest; extra == 'develop'
Requires-Dist: hatchling; extra == 'develop'
Requires-Dist: pytest; extra == 'develop'
Requires-Dist: pytest-cov; extra == 'develop'
Requires-Dist: ruff; extra == 'develop'
Requires-Dist: twine; extra == 'develop'
Requires-Dist: wheel; extra == 'develop'
